{
  "last_updated": "2024-07-01T17:38:30+00:00",
  "activity": [
    {
      "type": "pr_collaborated",
      "title": "coronasafe/care#2284",
      "time": "2024-07-01T17:38:30+00:00",
      "link": "https://github.com/coronasafe/care/pull/2284",
      "text": "Production Release v24.27.0",
      "collaborated_with": [
        "khavinshankar",
        "sainak",
        "vigneshhari",
        "Ashesh3"
      ]
    },
    {
      "type": "pr_collaborated",
      "title": "coronasafe/care_fe#8098",
      "time": "2024-07-01T17:38:03+00:00",
      "link": "https://github.com/coronasafe/care_fe/pull/8098",
      "text": "Production Release v24.27.0",
      "collaborated_with": [
        "rithviknishad",
        "khavinshankar",
        "Aryanshu919",
        "Ashesh3"
      ]
    },
    {
      "type": "issue_opened",
      "title": "coronasafe/care_fe#8091",
      "time": "2024-06-27T13:50:00+00:00",
      "link": "https://github.com/coronasafe/care_fe/issues/8091",
      "text": "Allow Configuration of Meta Description and update the default"
    }
  ],
  "open_prs": [
    {
      "link": "https://github.com/coronasafe/care_fe/pull/6670",
      "title": "Add Medispeak for Preview on Care",
      "stale_for": 202,
      "labels": [
        "In Progress"
      ]
    }
  ],
  "authored_issue_and_pr": []
}